progressvertical/__init__.py
progressvertical/color_manager.py
progressvertical/interfaces.py
progressvertical/progress_manager.py
progressvertical/renderers.py
progressvertical/trackers.py
progressvertical-0.2.4.dist-info/licenses/LICENSE
progressvertical-0.2.4.dist-info/METADATA
progressvertical-0.2.4.dist-info/WHEEL
progressvertical-0.2.4.dist-info/top_level.txt
progressvertical-0.2.4.dist-info/RECORD
