Metadata-Version: 2.4
Name: progressvertical
Version: 0.2.4
Summary: Rendering vertical progress bars with custom colors and styles
Author-email: Jeferson Cardoso <jefersoncardoso.dev@gmail.com>
Maintainer-email: Jeferson Cardoso <jefersoncardoso.dev@gmail.com>
License-Expression: MIT
Project-URL: Homepage, https://github.com/cardosource/progressvertical
Project-URL: Source, https://github.com/cardosource/progressvertical
Project-URL: Issues, https://github.com/cardosource/progressvertical/issues
Project-URL: Documentation, https://github.com/cardosource/progressvertical#readme
Keywords: progress,progress-bar,cli,terminal,vertical
Classifier: Development Status :: 4 - Beta
Classifier: Intended Audience :: Developers
Classifier: Programming Language :: Python :: 3
Classifier: Operating System :: OS Independent
Classifier: Topic :: Software Development :: Libraries :: Python Modules
Classifier: Topic :: Utilities
Requires-Python: >=3.8
License-File: LICENSE
Requires-Dist: colorama>=0.4.6
Dynamic: license-file
